dv_cage_bridge/__init__.py
dv_cage_bridge/api/__init__.py
dv_cage_bridge/api/algorithm/__init__.py
dv_cage_bridge/api/algorithm/get_algo_logs.py
dv_cage_bridge/api/algorithm/post_event.py
dv_cage_bridge/api/cage/__init__.py
dv_cage_bridge/api/cage/get_attestation_token.py
dv_cage_bridge/api/cage/get_public_key.py
dv_cage_bridge/api/cage/get_transport_key.py
dv_cage_bridge/api/cage/put_secrets_secret.py
dv_cage_bridge/api/cage/rotate_storage_key.py
dv_cage_bridge/api/cage/rotate_transport_key.py
dv_cage_bridge/api/collaborator/__init__.py
dv_cage_bridge/api/collaborator/get_collaborator_status.py
dv_cage_bridge/api/collaborator/mount_collaborator.py
dv_cage_bridge/api/collaborator/unmount_collaborator.py
dv_cage_bridge/api/quality/__init__.py
dv_cage_bridge/api/quality/get_report.py
dv_cage_bridge/api/quality/start_quality_validation.py
dv_cage_bridge/client.py
dv_cage_bridge/errors.py
dv_cage_bridge/models/__init__.py
dv_cage_bridge/models/algo_log.py
dv_cage_bridge/models/algo_log_log.py
dv_cage_bridge/models/collaborator_status.py
dv_cage_bridge/models/finished_report.py
dv_cage_bridge/models/finished_report_error_item.py
dv_cage_bridge/models/finished_report_fail_item.py
dv_cage_bridge/models/finished_report_status.py
dv_cage_bridge/models/finished_report_success_item.py
dv_cage_bridge/models/finished_summary.py
dv_cage_bridge/models/finished_summary_status.py
dv_cage_bridge/models/get_attestation_token_nonce.py
dv_cage_bridge/models/get_collaborator_status_response_404.py
dv_cage_bridge/models/get_report_response_404.py
dv_cage_bridge/models/mount_collaborator_response_400.py
dv_cage_bridge/models/mount_collaborator_response_404.py
dv_cage_bridge/models/pending_report.py
dv_cage_bridge/models/pending_report_status.py
dv_cage_bridge/models/post_event_body.py
dv_cage_bridge/models/post_event_response_200.py
dv_cage_bridge/models/post_event_response_400.py
dv_cage_bridge/models/put_secrets_secret_body.py
dv_cage_bridge/models/put_secrets_secret_response_400.py
dv_cage_bridge-0.3.0.dist-info/METADATA
dv_cage_bridge-0.3.0.dist-info/WHEEL
dv_cage_bridge-0.3.0.dist-info/RECORD
